ctconnect_ineelhere/__init__.py
ctconnect_ineelhere/example.py
ctconnect_ineelhere-0.0.0.dist-info/entry_points.txt
ctconnect_ineelhere-0.0.0.dist-info/LICENSE
ctconnect_ineelhere-0.0.0.dist-info/METADATA
ctconnect_ineelhere-0.0.0.dist-info/WHEEL
ctconnect_ineelhere-0.0.0.dist-info/RECORD
